odoo/addons/odoo_project/README.rst
odoo/addons/odoo_project/__init__.py
odoo/addons/odoo_project/__manifest__.py
odoo/addons/odoo_project/data/queue_job.xml
odoo/addons/odoo_project/models/__init__.py
odoo/addons/odoo_project/models/odoo_module_branch.py
odoo/addons/odoo_project/models/odoo_project.py
odoo/addons/odoo_project/models/odoo_project_module.py
odoo/addons/odoo_project/models/odoo_repository.py
odoo/addons/odoo_project/readme/CONTRIBUTORS.md
odoo/addons/odoo_project/readme/DESCRIPTION.md
odoo/addons/odoo_project/security/ir.model.access.csv
odoo/addons/odoo_project/static/description/icon.png
odoo/addons/odoo_project/static/description/index.html
odoo/addons/odoo_project/tests/__init__.py
odoo/addons/odoo_project/tests/common.py
odoo/addons/odoo_project/tests/test_import_modules.py
odoo/addons/odoo_project/views/menu.xml
odoo/addons/odoo_project/views/odoo_module_branch.xml
odoo/addons/odoo_project/views/odoo_project.xml
odoo/addons/odoo_project/views/odoo_project_module.xml
odoo/addons/odoo_project/views/odoo_repository.xml
odoo/addons/odoo_project/wizards/__init__.py
odoo/addons/odoo_project/wizards/odoo_project_import_modules.py
odoo/addons/odoo_project/wizards/odoo_project_import_modules.xml
odoo_addon_odoo_project-16.0.1.0.1.dist-info/METADATA
odoo_addon_odoo_project-16.0.1.0.1.dist-info/WHEEL
odoo_addon_odoo_project-16.0.1.0.1.dist-info/top_level.txt
odoo_addon_odoo_project-16.0.1.0.1.dist-info/RECORD
